at_client_data/__init__.py
at_client_data/client/__init__.py
at_client_data/client/base.py
at_client_data/client/core.py
at_client_data/client/external.py
at_client_data/schema/__init__.py
at_client_data/schema/candlestick.py
at_client_data/schema/economics.py
at_client_data/schema/entry.py
at_client_data/schema/news.py
at_client_data/schema/quote.py
at_client_data/schema/stock/__init__.py
at_client_data/schema/stock/analyst.py
at_client_data/schema/stock/calendar.py
at_client_data/schema/stock/company.py
at_client_data/schema/stock/financial.py
at_client_data/schema/stock/similarity.py
at_client_data-0.2.3.dist-info/licenses/LICENSE
at_client_data-0.2.3.dist-info/METADATA
at_client_data-0.2.3.dist-info/WHEEL
at_client_data-0.2.3.dist-info/top_level.txt
at_client_data-0.2.3.dist-info/RECORD
